.gitignore
.travis.yml
CHANGES
LICENSE
MANIFEST.in
README.rst
TODO
requirements.txt
setup.cfg
setup.py
systest.py
Hyperkit.egg-info/PKG-INFO
Hyperkit.egg-info/SOURCES.txt
Hyperkit.egg-info/dependency_links.txt
Hyperkit.egg-info/entry_points.txt
Hyperkit.egg-info/not-zip-safe
Hyperkit.egg-info/requires.txt
Hyperkit.egg-info/top_level.txt
hyperkit/__init__.py
hyperkit/cloudinit.py
hyperkit/command.py
hyperkit/error.py
hyperkit/distro/__init__.py
hyperkit/distro/cirros.py
hyperkit/distro/distro.py
hyperkit/distro/fedora.py
hyperkit/distro/ubuntu.py
hyperkit/hypervisor/__init__.py
hyperkit/hypervisor/command.py
hyperkit/hypervisor/machine.py
hyperkit/hypervisor/qemu_img.py
hyperkit/hypervisor/vbox.py
hyperkit/hypervisor/vboxmanage.py
hyperkit/hypervisor/vmrun.py
hyperkit/hypervisor/vmware.py
hyperkit/spec/__init__.py
hyperkit/spec/auth.py
hyperkit/spec/hardware.py
hyperkit/spec/image.py
hyperkit/spec/spec.py
hyperkit/test/__init__.py
hyperkit/test/test_cloudinit.py
hyperkit/test/test_distro.py
hyperkit/test/test_hypervisor_command.py
hyperkit/test/test_hypervisor_machine.py
hyperkit/test/test_hypervisor_vbox.py
hyperkit/test/test_hypervisor_vmware.py
hyperkit/test/test_spec.py