Metadata-Version: 1.1
Name: Hyperkit
Version: 0.2
Summary: Hypervisor tools
Home-page: http://yaybu.com/
Author: Isotoma Limited
Author-email: support@isotoma.com
License: Apache Software License
Platform: UNKNOWN
Classifier: Intended Audience :: System Administrators
Classifier: Operating System :: POSIX
Classifier: License :: OSI Approved :: Apache Software License
